onegpt/__init__.py
onegpt/version.py
open_gpt/__init__.py
open_gpt/version.py
simple_gpt/__init__.py
simple_gpt/version.py
tests/__init__.py
onegpt-0.0.1.dist-info/METADATA
onegpt-0.0.1.dist-info/WHEEL
onegpt-0.0.1.dist-info/top_level.txt
onegpt-0.0.1.dist-info/RECORD
